odoo/addons/agreement_legal_sale/README.rst
odoo/addons/agreement_legal_sale/__init__.py
odoo/addons/agreement_legal_sale/__manifest__.py
odoo/addons/agreement_legal_sale/i18n/agreement_legal_sale.pot
odoo/addons/agreement_legal_sale/i18n/agreement_sale.pot
odoo/addons/agreement_legal_sale/i18n/de.po
odoo/addons/agreement_legal_sale/i18n/es.po
odoo/addons/agreement_legal_sale/i18n/es_AR.po
odoo/addons/agreement_legal_sale/i18n/fr.po
odoo/addons/agreement_legal_sale/i18n/pt.po
odoo/addons/agreement_legal_sale/i18n/pt_BR.po
odoo/addons/agreement_legal_sale/i18n/zh_CN.po
odoo/addons/agreement_legal_sale/models/__init__.py
odoo/addons/agreement_legal_sale/models/agreement.py
odoo/addons/agreement_legal_sale/models/sale_order.py
odoo/addons/agreement_legal_sale/readme/CONFIGURE.rst
odoo/addons/agreement_legal_sale/readme/CONTRIBUTORS.rst
odoo/addons/agreement_legal_sale/readme/CREDITS.rst
odoo/addons/agreement_legal_sale/readme/DESCRIPTION.rst
odoo/addons/agreement_legal_sale/readme/ROADMAP.rst
odoo/addons/agreement_legal_sale/readme/USAGE.rst
odoo/addons/agreement_legal_sale/static/description/icon.png
odoo/addons/agreement_legal_sale/static/description/index.html
odoo/addons/agreement_legal_sale/tests/__init__.py
odoo/addons/agreement_legal_sale/tests/test_sale_order.py
odoo/addons/agreement_legal_sale/views/agreement.xml
odoo/addons/agreement_legal_sale/views/sale_order.xml
odoo14_addon_agreement_legal_sale-14.0.1.0.1.dist-info/METADATA
odoo14_addon_agreement_legal_sale-14.0.1.0.1.dist-info/WHEEL
odoo14_addon_agreement_legal_sale-14.0.1.0.1.dist-info/top_level.txt
odoo14_addon_agreement_legal_sale-14.0.1.0.1.dist-info/RECORD
